zarinpal/__init__.py
zarinpal/errors.py
zarinpal/main.py
zarinpal/models.py
python_zarinpal-1.0.0.dist-info/LICENSE
python_zarinpal-1.0.0.dist-info/METADATA
python_zarinpal-1.0.0.dist-info/WHEEL
python_zarinpal-1.0.0.dist-info/top_level.txt
python_zarinpal-1.0.0.dist-info/RECORD
